{
  "root": "/home/goe/projects/nextgen-server/",
  "swing.main.src": "swing/src/main/java",
  "swing.test.src": "swing/src/test/java",
  "swing.web.src": "swing/src/main/web",
  "swing.test.resources": "swing/src/test/resources",
  "swing.main.resources": "swing/src/main/resources",
  "core.main.src": "core/src/main/java",
  "core.test.src": "core/src/test/java",
  "core.web.src": "core/src/main/web",
  "core.test.resources": "core/src/test/resources",
  "core.main.resources": "core/src/main/resources",
  "server.main.src": "server/src/main/java",
  "server.test.src": "server/src/test/java",
  "server.web.src": "server/src/main/web",
  "server.test.resources": "server/src/test/resources",
  "server.main.resources": "server/src/main/resources"
}